odoo/addons/mgmtsystem_claim/README.rst
odoo/addons/mgmtsystem_claim/__init__.py
odoo/addons/mgmtsystem_claim/__manifest__.py
odoo/addons/mgmtsystem_claim/data/automated_reminder.xml
odoo/addons/mgmtsystem_claim/data/claim_sequence.xml
odoo/addons/mgmtsystem_claim/data/email_template.xml
odoo/addons/mgmtsystem_claim/data/mgmtsystem_claim_stage.xml
odoo/addons/mgmtsystem_claim/i18n/de.po
odoo/addons/mgmtsystem_claim/i18n/es.po
odoo/addons/mgmtsystem_claim/i18n/fr.po
odoo/addons/mgmtsystem_claim/i18n/it.po
odoo/addons/mgmtsystem_claim/i18n/mgmtsystem_claim.pot
odoo/addons/mgmtsystem_claim/i18n/nb.po
odoo/addons/mgmtsystem_claim/i18n/pt_BR.po
odoo/addons/mgmtsystem_claim/i18n/sl.po
odoo/addons/mgmtsystem_claim/i18n/sv.po
odoo/addons/mgmtsystem_claim/i18n/vi.po
odoo/addons/mgmtsystem_claim/models/__init__.py
odoo/addons/mgmtsystem_claim/models/mgmtsystem_claim.py
odoo/addons/mgmtsystem_claim/models/mgmtsystem_claim_stage.py
odoo/addons/mgmtsystem_claim/models/res_partner.py
odoo/addons/mgmtsystem_claim/readme/CONFIGURE.md
odoo/addons/mgmtsystem_claim/readme/CONTRIBUTORS.md
odoo/addons/mgmtsystem_claim/readme/DESCRIPTION.md
odoo/addons/mgmtsystem_claim/readme/USAGE.md
odoo/addons/mgmtsystem_claim/security/ir.model.access.csv
odoo/addons/mgmtsystem_claim/security/mgmtsystem_claim_security.xml
odoo/addons/mgmtsystem_claim/static/description/icon.png
odoo/addons/mgmtsystem_claim/static/description/index.html
odoo/addons/mgmtsystem_claim/tests/__init__.py
odoo/addons/mgmtsystem_claim/tests/test_create_claim.py
odoo/addons/mgmtsystem_claim/views/menus.xml
odoo/addons/mgmtsystem_claim/views/mgmtsystem_claim.xml
odoo/addons/mgmtsystem_claim/views/mgmtsystem_claim_stage.xml
odoo/addons/mgmtsystem_claim/views/res_partner_views.xml
odoo_addon_mgmtsystem_claim-18.0.1.0.0.5.dist-info/METADATA
odoo_addon_mgmtsystem_claim-18.0.1.0.0.5.dist-info/WHEEL
odoo_addon_mgmtsystem_claim-18.0.1.0.0.5.dist-info/top_level.txt
odoo_addon_mgmtsystem_claim-18.0.1.0.0.5.dist-info/RECORD
